Metadata-Version: 2.1
Name: hello-world-tasd
Version: 0.0.1
Summary: Gaussian and Binomial distributions
Home-page: UNKNOWN
Author-email: vghgiud@gmail.com
License: UNKNOWN
Platform: UNKNOWN
